{
  "appSettings": {
    "DefaultAppPath": "D:\\Sunup\\bin\\Debug\\net8.0\\deployedApps\\Demo"
  },
  "Logging": {
    "LogLevel": {
      "Default": "Debug",
      "System": "Information",
      "Microsoft": "Information",
      "Grpc": "Debug"
    }
  },
  "AllowedHosts": "*",
  "Kestrel": {
    "Endpoints": {
      "HttpsInlineCertFile": {
        "Url": "http://localhost:9001",
        //"Certificate": {
        //  "Path": "SampleCertificate.pfx",
        //  "Password": "SampleCertificate"
        //}
      }
    }
  }
}